gluetube/VERSION
gluetube/__init__.py
gluetube/autodiscovery.py
gluetube/command.py
gluetube/config.py
gluetube/db.py
gluetube/exception.py
gluetube/gluetube.py
gluetube/gluetubed.py
gluetube/pipeline.py
gluetube/putil.py
gluetube/runner.py
gluetube/util.py
gluetube/cfg/gluetube.cfg
gluetube/connectors/__init__.py
tests/__init__.py
tests/test_autodiscovery.py
tests/test_command.py
tests/test_config.py
tests/test_db.py
tests/test_gluetubed.py
tests/test_runner.py
tests/test_util.py
tests/pipeline_dir/pyfile_test.py
tests/pipeline_dir/test_1/example_pipeline1.py
tests/pipeline_dir/test_1/example_pipeline2.py
gluetube-0.1.1.dist-info/LICENSE
gluetube-0.1.1.dist-info/METADATA
gluetube-0.1.1.dist-info/WHEEL
gluetube-0.1.1.dist-info/entry_points.txt
gluetube-0.1.1.dist-info/top_level.txt
gluetube-0.1.1.dist-info/RECORD
