Metadata-Version: 2.1
Name: gluetube
Version: 0.1.1
Summary: A lightweight python script scheduler
Home-page: https://github.com/ctomkow/gluetube
Author: Craig Tomkow
Author-email: ctomkow@gmail.com
License: MIT
Classifier: Programming Language :: Python :: 3
Classifier: Programming Language :: Python :: 3.6
Classifier: Programming Language :: Python :: 3.7
Classifier: Programming Language :: Python :: 3.8
Classifier: Programming Language :: Python :: 3.9
Classifier: Programming Language :: Python :: 3.10
Classifier: Programming Language :: Python :: 3.11
License-File: LICENSE
Requires-Dist: python-daemon (<3.0.0,>=2.3.1)
Requires-Dist: apscheduler (<4.0.0,>=3.9.1)
Requires-Dist: prettytable (==2.5.0)
Requires-Dist: jinja2 (==3.0.3)
Requires-Dist: cryptography (<39.0.0,>=38.0.4)
